CtfWiki20171227/README.md
CtfWiki20171227/__init__.py
CtfWiki20171227/__main__.py
CtfWiki20171227/file.epub
CtfWiki20171227/index.html
CtfWiki20171227/css/__init__.py
CtfWiki20171227/css/annotations.css
CtfWiki20171227/css/main.css
CtfWiki20171227/css/normalize.css
CtfWiki20171227/css/popup.css
CtfWiki20171227/font/__init__.py
CtfWiki20171227/font/fontello.eot
CtfWiki20171227/font/fontello.svg
CtfWiki20171227/font/fontello.ttf
CtfWiki20171227/font/fontello.woff
CtfWiki20171227/img/__init__.py
CtfWiki20171227/img/annotator-glyph-sprite.png
CtfWiki20171227/img/annotator-icon-sprite.png
CtfWiki20171227/img/apple-touch-icon.png
CtfWiki20171227/img/cancelfullscreen.png
CtfWiki20171227/img/close.png
CtfWiki20171227/img/fullscreen.png
CtfWiki20171227/img/loader.gif
CtfWiki20171227/img/menu-icon.png
CtfWiki20171227/img/save.png
CtfWiki20171227/img/saved.png
CtfWiki20171227/img/settings-s.png
CtfWiki20171227/img/settings.png
CtfWiki20171227/img/star.png
CtfWiki20171227/js/__init__.py
CtfWiki20171227/js/epub.js
CtfWiki20171227/js/epub.min.js
CtfWiki20171227/js/epub.min.map
CtfWiki20171227/js/hooks.min.js
CtfWiki20171227/js/hooks.min.map
CtfWiki20171227/js/reader.js
CtfWiki20171227/js/reader.js.map
CtfWiki20171227/js/reader.min.js
CtfWiki20171227/js/reader.min.map
CtfWiki20171227/js/hooks/__init__.py
CtfWiki20171227/js/hooks/extensions/__init__.py
CtfWiki20171227/js/hooks/extensions/highlight.js
CtfWiki20171227/js/libs/__init__.py
CtfWiki20171227/js/libs/jquery.min.js
CtfWiki20171227/js/libs/localforage.min.js
CtfWiki20171227/js/libs/screenfull.js
CtfWiki20171227/js/libs/screenfull.min.js
CtfWiki20171227/js/libs/zip.min.js
CtfWiki20171227/js/plugins/__init__.py
CtfWiki20171227/js/plugins/hypothesis.js
CtfWiki20171227/js/plugins/search.js
ctf_wiki_2017_12_27-2024.3.3.0.dist-info/METADATA
ctf_wiki_2017_12_27-2024.3.3.0.dist-info/WHEEL
ctf_wiki_2017_12_27-2024.3.3.0.dist-info/entry_points.txt
ctf_wiki_2017_12_27-2024.3.3.0.dist-info/top_level.txt
ctf_wiki_2017_12_27-2024.3.3.0.dist-info/RECORD
